pieqt/App.py
pieqt/__init__.py
pieqt/pieqt.py
pieqt-0.0.1.dist-info/LICENSE
pieqt-0.0.1.dist-info/METADATA
pieqt-0.0.1.dist-info/WHEEL
pieqt-0.0.1.dist-info/top_level.txt
pieqt-0.0.1.dist-info/RECORD
