Metadata-Version: 2.1
Name: pieqt
Version: 0.0.1
Summary: simple description
Home-page: https://github.com/rivenblades/pieqt
Author: kostas_petsis
Author-email: kostaspetsis@outlook.com
License: MIT License
